krl_rover/__init__.py
krl_rover/rover_control.py
krl_rover-0.1.0.dist-info/LICENSE.txt
krl_rover-0.1.0.dist-info/METADATA
krl_rover-0.1.0.dist-info/WHEEL
krl_rover-0.1.0.dist-info/top_level.txt
krl_rover-0.1.0.dist-info/RECORD
