Metadata-Version: 2.1
Name: krl_rover
Version: 0.1.0
Summary: A library to control a rover using Raspberry Pi
Home-page: https://github.com/Deshik7177/krl_rover
Author: deshik7177
Author-email: pdhanadeshik7177@gmail.com
Classifier: Programming Language :: Python :: 3
Classifier: License :: OSI Approved :: MIT License
Classifier: Operating System :: OS Independent
Requires-Python: >=3.6
License-File: LICENSE.txt
